{
  "cities": [
    {
      "id": "15fc2a5e-0891-4474-8bad-ecc2d36332cf",
      "name": "Villa Maria"
    },
    {
      "id": "8b48c338-b08c-4c31-8d5f-963ef9feea9f",
      "name": "Campana"
    },
    {
      "id": "4562c463-8680-45aa-9a11-d7dd5b52bacf",
      "name": "San Nicolas"
    },
    {
      "id": "0aba3d2c-ca83-4f72-b226-a4942341841a",
      "name": "Rio Cuarto"
    },
    {
      "id": "1196b70b-8ad4-489f-b148-7d7a305dfff1",
      "name": "La Falda"
    }
  ],
  "trips": [
    {
      "id": "30e47bd9-0331-446a-bcdd-9780e496d77b",
      "originId": "",
      "destinationId": "",
      "departureTime": "",
      "price": 0,
      "stops": [
        {
          "location": "San tasfarat",
          "time": "20:00",
          "stopTime": 40
        },
        {
          "location": "Santa teresita",
          "time": "10:00",
          "stopTime": 20
        },
        {
          "location": "afsdfsdf",
          "time": "13:00",
          "stopTime": 10
        },
        {
          "location": "Afsasdfasdf",
          "time": "15:00",
          "stopTime": 2
        },
        {
          "location": "asdfasdgf",
          "time": "19:00",
          "stopTime": 5
        },
        {
          "location": "Santa teresita",
          "time": "10:00",
          "stopTime": 20
        }
      ]
    }
  ]
}